{
  "generated_at_local": "2026-06-30T13:13:25",
  "target": 5,
  "window_capacity_wd": 11,
  "window_noshow_days": 32,
  "carvago": {
    "backlog_now": 10,
    "arrived_today": 22,
    "done_today": 20,
    "start_of_day": 8,
    "promised_today": 35,
    "realization": 0.8581,
    "no_show": 0.1419,
    "inflow": 30.0,
    "capacity": 26.0,
    "capacity_named": 21.6,
    "capacity_other": 4.4,
    "capacity_by_owner": {
      "Daniel Forman": 7.0,
      "Marek Moťovský": 6.9,
      "Martin Linhart": 4.4,
      "Ostatní / systém": 4.4,
      "Daniel Noga": 3.1,
      "Vladimír Uher": 0.3
    },
    "end_of_day": 12.0,
    "extra_ca_for_target": 7.0,
    "extra_people_for_target": 2,
    "pipeline": {
      "overdue": 9,
      "today": 10,
      "tomorrow": 15
    }
  },
  "cebia": {
    "backlog_now": 0,
    "arrived_today": 0,
    "done_today": 0,
    "start_of_day": 0,
    "promised_today": 2,
    "realization": 0.9155,
    "no_show": 0.0845,
    "inflow": 1.8,
    "capacity": null,
    "capacity_source": "casehistory_prep_done",
    "end_of_day": null,
    "note": "Cebia Done date not populated; capacity via CaseHistory Prep->Done (Q16)",
    "pipeline": {
      "overdue": 0,
      "today": 1,
      "tomorrow": 3
    }
  }
}