{
  "generated_at_local": "2026-07-02T05:34:44",
  "target": 5,
  "window_capacity_wd": 11,
  "window_noshow_days": 32,
  "carvago": {
    "backlog_now": 3,
    "arrived_today": 14,
    "done_today": 0,
    "start_of_day": -11,
    "promised_today": 0,
    "realization": 0.862,
    "no_show": 0.138,
    "inflow": 0.0,
    "capacity": 24.2,
    "capacity_named": 20.5,
    "capacity_other": 3.7,
    "capacity_by_owner": {
      "Daniel Forman": 6.6,
      "Marek Moťovský": 6.5,
      "Martin Linhart": 4.1,
      "Ostatní / systém": 3.7,
      "Daniel Noga": 3.1,
      "Vladimír Uher": 0.3
    },
    "end_of_day": 0,
    "extra_ca_for_target": 0,
    "extra_people_for_target": 0,
    "pipeline": {
      "overdue": 14,
      "today": 11,
      "tomorrow": 10
    }
  },
  "cebia": {
    "backlog_now": 0,
    "arrived_today": 0,
    "done_today": 0,
    "start_of_day": 0,
    "promised_today": 10,
    "realization": 0.92,
    "no_show": 0.08,
    "inflow": 9.2,
    "capacity": null,
    "capacity_source": "casehistory_prep_done",
    "end_of_day": null,
    "note": "Cebia Done date not populated; capacity via CaseHistory Prep->Done (Q16)",
    "pipeline": {
      "overdue": 0,
      "today": 8,
      "tomorrow": 1
    }
  }
}