{
  "generated_at_local": "2026-07-03T08:10:43",
  "target": 5,
  "window_capacity_wd": 11,
  "window_noshow_days": 32,
  "carvago": {
    "backlog_now": 5,
    "arrived_today": 3,
    "done_today": 0,
    "start_of_day": 2,
    "promised_today": 25,
    "realization": 0.8674,
    "no_show": 0.1326,
    "inflow": 21.7,
    "capacity": 23.7,
    "capacity_named": 20.2,
    "capacity_other": 3.5,
    "capacity_by_owner": {
      "Daniel Forman": 6.6,
      "Marek Moťovský": 6.1,
      "Martin Linhart": 4.2,
      "Ostatní / systém": 3.5,
      "Daniel Noga": 3.0,
      "Vladimír Uher": 0.3
    },
    "end_of_day": 0,
    "extra_ca_for_target": 0,
    "extra_people_for_target": 0,
    "pipeline": {
      "overdue": 9,
      "today": 21,
      "tomorrow": 6
    }
  },
  "cebia": {
    "backlog_now": 0,
    "arrived_today": 0,
    "done_today": 0,
    "start_of_day": 0,
    "promised_today": 3,
    "realization": 0.8941,
    "no_show": 0.1059,
    "inflow": 2.7,
    "capacity": null,
    "capacity_source": "casehistory_prep_done",
    "end_of_day": null,
    "note": "Cebia Done date not populated; capacity via CaseHistory Prep->Done (Q16)",
    "pipeline": {
      "overdue": 3,
      "today": 3,
      "tomorrow": 0
    }
  }
}