{
  "schema_version": 1,
  "generated_at_utc": "2026-05-28T06:19:19.010565+00:00",
  "generated_at_local": "2026-05-28T08:19:19.010565+02:00",
  "sf_base_url": "https://carvago.lightning.force.com",
  "month_label": "May 2026",
  "tier1": {
    "total": 1974,
    "closed": 1334,
    "phase2": 572,
    "ip_total": 68
  },
  "status_breakdown": {
    "Auditor selection": 12,
    "Awaiting Selection": 68,
    "Audit result": 15,
    "New CA": 9,
    "Data validation and completion": 5,
    "CarAudit preparation": 1,
    "CarAudit Done": 431,
    "Audit order": 45,
    "Car check": 48,
    "CarAudit Closed": 1334,
    "VIN Check": 6
  },
  "closed_reasons": {
    "REJECT New CA": 163,
    "REJECT Data Validation": 248,
    "REJECT Car Check": 521,
    "REJECT VIN Check": 119,
    "REJECT Awaiting Selection": 127
  },
  "country_breakdown": {
    "DE": {
      "ip": 34,
      "cl": 0,
      "cc": 24,
      "vin": 3,
      "newca": 7
    },
    "KR": {
      "ip": 2,
      "cl": 0,
      "cc": 0,
      "vin": 0,
      "newca": 2
    },
    "PL": {
      "ip": 3,
      "cl": 0,
      "cc": 3,
      "vin": 0,
      "newca": 0
    },
    "IT": {
      "ip": 1,
      "cl": 0,
      "cc": 1,
      "vin": 0,
      "newca": 0
    },
    "SK": {
      "ip": 1,
      "cl": 0,
      "cc": 1,
      "vin": 0,
      "newca": 0
    },
    "NL": {
      "ip": 2,
      "cl": 0,
      "cc": 2,
      "vin": 0,
      "newca": 0
    },
    "CZ": {
      "ip": 1,
      "cl": 0,
      "cc": 1,
      "vin": 0,
      "newca": 0
    },
    "BE": {
      "ip": 2,
      "cl": 0,
      "cc": 2,
      "vin": 0,
      "newca": 0
    },
    "SE": {
      "ip": 1,
      "cl": 0,
      "cc": 1,
      "vin": 0,
      "newca": 0
    }
  },
  "agent_breakdown": {
    "Agent1": 14,
    "Agent2": 10,
    "Neprideleno": 7,
    "Agent4": 1,
    "Agent5": 3
  },
  "nedovolano": [
    {
      "id": "500MI00000nnZtJYAU",
      "cn": "00182898",
      "country": "DE",
      "agent": "Agent1",
      "ageH": 56,
      "ageW": 26.02,
      "isN": false,
      "nCnt": 0,
      "ctCnt": 0,
      "lastType": null,
      "lastD": "2026-05-26T12:40:29.000+0000",
      "lastBy": "Anna Katharina Plath",
      "incs": [
        {
          "subject": "CA - reserved for another customer",
          "eta": "2026-05-27",
          "createdDate": "2026-05-26T12:40:29.000+0000",
          "createdBy": "Anna Katharina Plath"
        }
      ],
      "potClose": false,
      "potSpanH": null,
      "pref": true
    },
    {
      "id": "500MI00000nndFYYAY",
      "cn": "00182927",
      "country": "DE",
      "agent": "Agent2",
      "ageH": 56,
      "ageW": 26.02,
      "isN": true,
      "nCnt": 2,
      "ctCnt": 2,
      "lastType": "nedov",
      "lastD": "2026-05-26T07:50:34.000+0000",
      "lastBy": "Call Center Conectart1",
      "incs": [
        {
          "subject": "CA - reserved for another customer",
          "eta": "2026-05-28",
          "createdDate": "2026-05-26T09:07:12.000+0000",
          "createdBy": "Anna Katharina Plath"
        }
      ],
      "potClose": false,
      "potSpanH": 1.39,
      "pref": true
    },
    {
      "id": "500MI00000nqxXeYAI",
      "cn": "00183297",
      "country": "DE",
      "agent": "Agent1",
      "ageH": 51,
      "ageW": 20.66,
      "isN": true,
      "nCnt": 1,
      "ctCnt": 1,
      "lastType": "nedov",
      "lastD": "2026-05-26T12:33:42.000+0000",
      "lastBy": "Pavel Tran Son",
      "incs": [
        {
          "subject": "CA - reserved for another customer",
          "eta": "2026-05-28",
          "createdDate": "2026-05-27T06:16:08.000+0000",
          "createdBy": "Martin Farkas"
        }
      ],
      "potClose": false,
      "potSpanH": null,
      "pref": false
    },
    {
      "id": "500MI00000nqxXfYAI",
      "cn": "00183298",
      "country": "PL",
      "agent": null,
      "ageH": 51,
      "ageW": 20.68,
      "isN": false,
      "nCnt": 0,
      "ctCnt": 0,
      "lastType": null,
      "lastD": "2026-05-25T11:20:46.000+0000",
      "lastBy": "Daniel Noga",
      "incs": [
        {
          "subject": "CA - consultation of previous damage",
          "eta": "2026-05-27",
          "createdDate": "2026-05-25T11:20:46.000+0000",
          "createdBy": "Daniel Noga"
        }
      ],
      "potClose": false,
      "potSpanH": null,
      "pref": false
    },
    {
      "id": "500MI00000nrGP3YAM",
      "cn": "00183384",
      "country": "DE",
      "agent": "Agent1",
      "ageH": 50,
      "ageW": 19.57,
      "isN": false,
      "nCnt": 0,
      "ctCnt": 0,
      "lastType": null,
      "lastD": "2026-05-26T08:32:45.000+0000",
      "lastBy": "Martin Farkas",
      "incs": [
        {
          "subject": "CA - reserved for another customer",
          "eta": "2026-05-27",
          "createdDate": "2026-05-26T08:32:45.000+0000",
          "createdBy": "Martin Farkas"
        }
      ],
      "potClose": false,
      "potSpanH": null,
      "pref": false
    },
    {
      "id": "500MI00000nrGPEYA2",
      "cn": "00183395",
      "country": "DE",
      "agent": "Agent1",
      "ageH": 49,
      "ageW": 19.34,
      "isN": false,
      "nCnt": 0,
      "ctCnt": 1,
      "lastType": "messaging",
      "lastD": "2026-05-26T07:43:19.000+0000",
      "lastBy": "Call Center Conectart1",
      "incs": [
        {
          "subject": "CA - reserved for another customer",
          "eta": "2026-05-27",
          "createdDate": "2026-05-26T10:56:28.000+0000",
          "createdBy": "Martin Farkas"
        }
      ],
      "potClose": false,
      "potSpanH": null,
      "pref": false
    },
    {
      "id": "500MI00000nvq0tYAA",
      "cn": "00183830",
      "country": "PL",
      "agent": null,
      "ageH": 8,
      "ageW": 8.02,
      "isN": false,
      "nCnt": 0,
      "ctCnt": 0,
      "lastType": null,
      "lastD": null,
      "lastBy": null,
      "incs": [],
      "potClose": false,
      "potSpanH": null,
      "pref": true
    },
    {
      "id": "500MI00000nvuCXYAY",
      "cn": "00183834",
      "country": "DE",
      "agent": "Agent2",
      "ageH": 8,
      "ageW": 8.02,
      "isN": true,
      "nCnt": 3,
      "ctCnt": 3,
      "lastType": "callback",
      "lastD": "2026-05-27T13:29:27.000+0000",
      "lastBy": "Monika Selmová",
      "incs": [],
      "potClose": true,
      "potSpanH": 5.28,
      "pref": true
    },
    {
      "id": "500MI00000nw5mQYAQ",
      "cn": "00183861",
      "country": "DE",
      "agent": "Agent1",
      "ageH": 8,
      "ageW": 7.95,
      "isN": false,
      "nCnt": 0,
      "ctCnt": 0,
      "lastType": null,
      "lastD": "2026-05-27T08:19:32.000+0000",
      "lastBy": "Vladimír Uher",
      "incs": [
        {
          "subject": "CA - reserved for another customer",
          "eta": "2026-05-28",
          "createdDate": "2026-05-27T08:19:32.000+0000",
          "createdBy": "Vladimír Uher"
        }
      ],
      "potClose": false,
      "potSpanH": null,
      "pref": true
    },
    {
      "id": "500MI00000nw96nYAA",
      "cn": "00183863",
      "country": "IT",
      "agent": null,
      "ageH": 8,
      "ageW": 8.02,
      "isN": false,
      "nCnt": 0,
      "ctCnt": 0,
      "lastType": null,
      "lastD": null,
      "lastBy": null,
      "incs": [],
      "potClose": false,
      "potSpanH": null,
      "pref": true
    },
    {
      "id": "500MI00000nwf9tYAA",
      "cn": "00183888",
      "country": "SK",
      "agent": "Agent2",
      "ageH": 8,
      "ageW": 7.92,
      "isN": false,
      "nCnt": 0,
      "ctCnt": 0,
      "lastType": null,
      "lastD": null,
      "lastBy": null,
      "incs": [],
      "potClose": false,
      "potSpanH": null,
      "pref": false
    },
    {
      "id": "500MI00000nwoVfYAI",
      "cn": "00183901",
      "country": "DE",
      "agent": "Agent2",
      "ageH": 1,
      "ageW": 1.23,
      "isN": true,
      "nCnt": 1,
      "ctCnt": 1,
      "lastType": "nedov",
      "lastD": "2026-05-27T13:47:44.000+0000",
      "lastBy": "Monika Selmová",
      "incs": [],
      "potClose": false,
      "potSpanH": null,
      "pref": true
    },
    {
      "id": "500MI00000nx1FHYAY",
      "cn": "00183920",
      "country": "DE",
      "agent": "Agent1",
      "ageH": 3,
      "ageW": 3.44,
      "isN": true,
      "nCnt": 4,
      "ctCnt": 4,
      "lastType": "messaging",
      "lastD": "2026-05-27T13:33:36.000+0000",
      "lastBy": "Call Center Conectart1",
      "incs": [],
      "potClose": false,
      "potSpanH": null,
      "pref": false
    },
    {
      "id": "500MI00000nx8yGYAQ",
      "cn": "00183913",
      "country": "DE",
      "agent": "Agent2",
      "ageH": 5,
      "ageW": 5.16,
      "isN": false,
      "nCnt": 0,
      "ctCnt": 0,
      "lastType": null,
      "lastD": "2026-05-27T10:00:21.000+0000",
      "lastBy": "Anna Katharina Plath",
      "incs": [
        {
          "subject": "CA - reserved for another customer",
          "eta": "2026-05-28",
          "createdDate": "2026-05-27T10:00:21.000+0000",
          "createdBy": "Anna Katharina Plath"
        }
      ],
      "potClose": false,
      "potSpanH": null,
      "pref": true
    },
    {
      "id": "500MI00000nxB03YAE",
      "cn": "00183911",
      "country": "NL",
      "agent": null,
      "ageH": 5,
      "ageW": 5.04,
      "isN": false,
      "nCnt": 0,
      "ctCnt": 0,
      "lastType": null,
      "lastD": null,
      "lastBy": null,
      "incs": [],
      "potClose": false,
      "potSpanH": null,
      "pref": true
    },
    {
      "id": "500MI00000nxG1SYAU",
      "cn": "00183949",
      "country": "DE",
      "agent": "Agent1",
      "ageH": 3,
      "ageW": 3.47,
      "isN": true,
      "nCnt": 1,
      "ctCnt": 2,
      "lastType": "nedov",
      "lastD": "2026-05-27T12:37:07.000+0000",
      "lastBy": "Call Center Conectart1",
      "incs": [],
      "potClose": false,
      "potSpanH": null,
      "pref": false
    },
    {
      "id": "500MI00000nxG1TYAU",
      "cn": "00183950",
      "country": "DE",
      "agent": "Agent1",
      "ageH": 3,
      "ageW": 3.43,
      "isN": false,
      "nCnt": 0,
      "ctCnt": 2,
      "lastType": "messaging",
      "lastD": "2026-05-27T12:34:01.000+0000",
      "lastBy": "Call Center Conectart1",
      "incs": [],
      "potClose": false,
      "potSpanH": null,
      "pref": false
    },
    {
      "id": "500MI00000nxVYDYA2",
      "cn": "00183942",
      "country": "DE",
      "agent": "Agent1",
      "ageH": 5,
      "ageW": 5.02,
      "isN": false,
      "nCnt": 0,
      "ctCnt": 0,
      "lastType": null,
      "lastD": null,
      "lastBy": null,
      "incs": [],
      "potClose": false,
      "potSpanH": null,
      "pref": true
    },
    {
      "id": "500MI00000nxXlUYAU",
      "cn": "00183997",
      "country": "CZ",
      "agent": "Agent2",
      "ageH": 3,
      "ageW": 3.41,
      "isN": false,
      "nCnt": 0,
      "ctCnt": 0,
      "lastType": null,
      "lastD": null,
      "lastBy": null,
      "incs": [],
      "potClose": false,
      "potSpanH": null,
      "pref": false
    },
    {
      "id": "500MI00000nxZScYAM",
      "cn": "00184004",
      "country": "DE",
      "agent": "Agent5",
      "ageH": 3,
      "ageW": 2.9,
      "isN": false,
      "nCnt": 0,
      "ctCnt": 0,
      "lastType": null,
      "lastD": null,
      "lastBy": null,
      "incs": [],
      "potClose": false,
      "potSpanH": null,
      "pref": true
    },
    {
      "id": "500MI00000nxbYpYAI",
      "cn": "00183964",
      "country": "DE",
      "agent": "Agent5",
      "ageH": 4,
      "ageW": 3.55,
      "isN": true,
      "nCnt": 1,
      "ctCnt": 3,
      "lastType": "messaging",
      "lastD": "2026-05-27T12:32:16.000+0000",
      "lastBy": "Anna Katharina Plath",
      "incs": [],
      "potClose": false,
      "potSpanH": null,
      "pref": true
    },
    {
      "id": "500MI00000nxchpYAA",
      "cn": "00183965",
      "country": "BE",
      "agent": null,
      "ageH": 4,
      "ageW": 3.7,
      "isN": false,
      "nCnt": 0,
      "ctCnt": 0,
      "lastType": null,
      "lastD": null,
      "lastBy": null,
      "incs": [],
      "potClose": false,
      "potSpanH": null,
      "pref": true
    },
    {
      "id": "500MI00000nxeuzYAA",
      "cn": "00183977",
      "country": "DE",
      "agent": "Agent2",
      "ageH": 3,
      "ageW": 3.45,
      "isN": false,
      "nCnt": 0,
      "ctCnt": 0,
      "lastType": null,
      "lastD": null,
      "lastBy": null,
      "incs": [],
      "potClose": false,
      "potSpanH": null,
      "pref": true
    },
    {
      "id": "500MI00000nxqT3YAI",
      "cn": "00184011",
      "country": "DE",
      "agent": "Agent2",
      "ageH": 2,
      "ageW": 2.17,
      "isN": false,
      "nCnt": 0,
      "ctCnt": 0,
      "lastType": null,
      "lastD": null,
      "lastBy": null,
      "incs": [],
      "potClose": false,
      "potSpanH": null,
      "pref": true
    },
    {
      "id": "500MI00000nxswPYAQ",
      "cn": "00184063",
      "country": "DE",
      "agent": "Agent2",
      "ageH": 1,
      "ageW": 0.7,
      "isN": false,
      "nCnt": 0,
      "ctCnt": 0,
      "lastType": null,
      "lastD": null,
      "lastBy": null,
      "incs": [],
      "potClose": false,
      "potSpanH": null,
      "pref": true
    },
    {
      "id": "500MI00000nxwDVYAY",
      "cn": "00184014",
      "country": "DE",
      "agent": "Agent1",
      "ageH": 2,
      "ageW": 2.18,
      "isN": true,
      "nCnt": 2,
      "ctCnt": 2,
      "lastType": "nedov",
      "lastD": "2026-05-27T12:41:41.000+0000",
      "lastBy": "Call Center Conectart1",
      "incs": [],
      "potClose": false,
      "potSpanH": null,
      "pref": false
    },
    {
      "id": "500MI00000nxxSvYAI",
      "cn": "00184035",
      "country": "DE",
      "agent": "Agent1",
      "ageH": 2,
      "ageW": 1.83,
      "isN": true,
      "nCnt": 2,
      "ctCnt": 2,
      "lastType": "nedov",
      "lastD": "2026-05-27T13:05:30.000+0000",
      "lastBy": "Call Center Conectart1",
      "incs": [],
      "potClose": false,
      "potSpanH": null,
      "pref": false
    },
    {
      "id": "500MI00000nxxSxYAI",
      "cn": "00184037",
      "country": "DE",
      "agent": "Agent1",
      "ageH": 2,
      "ageW": 1.84,
      "isN": false,
      "nCnt": 0,
      "ctCnt": 0,
      "lastType": null,
      "lastD": null,
      "lastBy": null,
      "incs": [],
      "potClose": false,
      "potSpanH": null,
      "pref": false
    },
    {
      "id": "500MI00000nxxSyYAI",
      "cn": "00184038",
      "country": "BE",
      "agent": "Agent1",
      "ageH": 2,
      "ageW": 1.86,
      "isN": false,
      "nCnt": 0,
      "ctCnt": 0,
      "lastType": null,
      "lastD": null,
      "lastBy": null,
      "incs": [],
      "potClose": false,
      "potSpanH": null,
      "pref": false
    },
    {
      "id": "500MI00000ny11pYAA",
      "cn": "00184010",
      "country": "PL",
      "agent": null,
      "ageH": 3,
      "ageW": 2.94,
      "isN": false,
      "nCnt": 0,
      "ctCnt": 0,
      "lastType": null,
      "lastD": null,
      "lastBy": null,
      "incs": [],
      "potClose": false,
      "potSpanH": null,
      "pref": true
    },
    {
      "id": "500MI00000ny4uAYAQ",
      "cn": "00184016",
      "country": "NL",
      "agent": "Agent4",
      "ageH": 2,
      "ageW": 2.13,
      "isN": false,
      "nCnt": 0,
      "ctCnt": 0,
      "lastType": null,
      "lastD": null,
      "lastBy": null,
      "incs": [],
      "potClose": false,
      "potSpanH": null,
      "pref": true
    },
    {
      "id": "500MI00000ny7QdYAI",
      "cn": "00184042",
      "country": "DE",
      "agent": "Agent1",
      "ageH": 2,
      "ageW": 1.8,
      "isN": false,
      "nCnt": 0,
      "ctCnt": 1,
      "lastType": "messaging",
      "lastD": "2026-05-27T12:31:16.000+0000",
      "lastBy": "Call Center Conectart1",
      "incs": [],
      "potClose": false,
      "potSpanH": null,
      "pref": true
    },
    {
      "id": "500MI00000nyBh8YAE",
      "cn": "00184057",
      "country": "DE",
      "agent": "Agent2",
      "ageH": 1,
      "ageW": 0.75,
      "isN": false,
      "nCnt": 0,
      "ctCnt": 0,
      "lastType": null,
      "lastD": null,
      "lastBy": null,
      "incs": [],
      "potClose": false,
      "potSpanH": null,
      "pref": true
    },
    {
      "id": "500MI00000nyH5AYAU",
      "cn": "00184060",
      "country": "DE",
      "agent": "Agent5",
      "ageH": 1,
      "ageW": 0.71,
      "isN": false,
      "nCnt": 0,
      "ctCnt": 0,
      "lastType": null,
      "lastD": null,
      "lastBy": null,
      "incs": [],
      "potClose": false,
      "potSpanH": null,
      "pref": true
    },
    {
      "id": "500MI00000nyMSuYAM",
      "cn": "00184066",
      "country": "SE",
      "agent": null,
      "ageH": 1,
      "ageW": 0.66,
      "isN": false,
      "nCnt": 0,
      "ctCnt": 0,
      "lastType": null,
      "lastD": null,
      "lastBy": null,
      "incs": [],
      "potClose": false,
      "potSpanH": null,
      "pref": true
    }
  ],
  "nedov_count": 9,
  "heatmap": {
    "matrix": [
      [
        1,
        0,
        0,
        0,
        0,
        2,
        2,
        17,
        25,
        23,
        39,
        52,
        27,
        59,
        122,
        44,
        30,
        22,
        14,
        20,
        10,
        15,
        7,
        8
      ],
      [
        2,
        2,
        0,
        1,
        2,
        0,
        4,
        7,
        23,
        44,
        59,
        40,
        52,
        51,
        55,
        32,
        37,
        20,
        22,
        23,
        14,
        13,
        11,
        4
      ],
      [
        3,
        2,
        0,
        2,
        0,
        1,
        1,
        25,
        18,
        33,
        25,
        39,
        34,
        34,
        74,
        33,
        26,
        24,
        13,
        6,
        6,
        15,
        7,
        4
      ],
      [
        1,
        1,
        3,
        1,
        0,
        0,
        2,
        9,
        21,
        26,
        31,
        27,
        32,
        21,
        60,
        18,
        30,
        11,
        9,
        4,
        6,
        7,
        3,
        7
      ],
      [
        1,
        0,
        0,
        0,
        0,
        0,
        2,
        8,
        10,
        14,
        19,
        19,
        22,
        17,
        33,
        8,
        16,
        3,
        9,
        3,
        11,
        2,
        2,
        4
      ],
      [
        3,
        1,
        0,
        0,
        0,
        0,
        0,
        2,
        7,
        8,
        9,
        6,
        6,
        6,
        7,
        2,
        6,
        11,
        6,
        4,
        2,
        6,
        4,
        1
      ],
      [
        3,
        0,
        0,
        0,
        0,
        0,
        0,
        0,
        3,
        5,
        3,
        3,
        8,
        4,
        8,
        9,
        3,
        4,
        8,
        6,
        6,
        6,
        2,
        5
      ]
    ],
    "days_per_dow": [
      5,
      5,
      5,
      4,
      4,
      4,
      4
    ],
    "total_cases": 2198,
    "start_date": "2026-04-27",
    "end_date": "2026-05-27"
  },
  "buffer_hourly": {
    "start_buffer": 57,
    "start_new_ca": 9,
    "start_car_check": 48,
    "current_buffer": 57,
    "current_new_ca": 9,
    "current_car_check": 48,
    "hours": [
      {
        "h": 8,
        "in": 3,
        "vin": 0,
        "rej": 3,
        "buffer_end": 57
      },
      {
        "h": 9,
        "in": null,
        "vin": null,
        "rej": null,
        "buffer_end": null
      },
      {
        "h": 10,
        "in": null,
        "vin": null,
        "rej": null,
        "buffer_end": null
      },
      {
        "h": 11,
        "in": null,
        "vin": null,
        "rej": null,
        "buffer_end": null
      },
      {
        "h": 12,
        "in": null,
        "vin": null,
        "rej": null,
        "buffer_end": null
      },
      {
        "h": 13,
        "in": null,
        "vin": null,
        "rej": null,
        "buffer_end": null
      },
      {
        "h": 14,
        "in": null,
        "vin": null,
        "rej": null,
        "buffer_end": null
      },
      {
        "h": 15,
        "in": null,
        "vin": null,
        "rej": null,
        "buffer_end": null
      },
      {
        "h": 16,
        "in": null,
        "vin": null,
        "rej": null,
        "buffer_end": null
      },
      {
        "h": 17,
        "in": null,
        "vin": null,
        "rej": null,
        "buffer_end": null
      }
    ],
    "projection_18": {
      "buffer": 57,
      "rate_per_h": 0.0,
      "delta_vs_now": 0
    }
  },
  "aws_split": {
    "cases": 70,
    "customers": 60,
    "solo": 41,
    "with_other": 19
  },
  "phase2_tables": {
    "statuses": [
      "Auditor selection",
      "Audit order",
      "Audit result",
      "CarAudit preparation"
    ],
    "preferred": {
      "Auditor selection": {
        "pref": 13,
        "nopref": 5
      },
      "Audit order": {
        "pref": 34,
        "nopref": 14
      },
      "Audit result": {
        "pref": 5,
        "nopref": 1
      },
      "CarAudit preparation": {
        "pref": 1,
        "nopref": 0
      }
    },
    "age": {
      "Auditor selection": {
        "lt2": {
          "pref": 12,
          "nopref": 4
        },
        "b23": {
          "pref": 1,
          "nopref": 1
        },
        "b35": {
          "pref": 0,
          "nopref": 0
        },
        "b57": {
          "pref": 0,
          "nopref": 0
        },
        "gt7": {
          "pref": 0,
          "nopref": 0
        }
      },
      "Audit order": {
        "lt2": {
          "pref": 26,
          "nopref": 12
        },
        "b23": {
          "pref": 0,
          "nopref": 2
        },
        "b35": {
          "pref": 3,
          "nopref": 0
        },
        "b57": {
          "pref": 5,
          "nopref": 0
        },
        "gt7": {
          "pref": 0,
          "nopref": 0
        }
      },
      "Audit result": {
        "lt2": {
          "pref": 5,
          "nopref": 0
        },
        "b23": {
          "pref": 0,
          "nopref": 0
        },
        "b35": {
          "pref": 0,
          "nopref": 0
        },
        "b57": {
          "pref": 0,
          "nopref": 1
        },
        "gt7": {
          "pref": 0,
          "nopref": 0
        }
      },
      "CarAudit preparation": {
        "lt2": {
          "pref": 1,
          "nopref": 0
        },
        "b23": {
          "pref": 0,
          "nopref": 0
        },
        "b35": {
          "pref": 0,
          "nopref": 0
        },
        "b57": {
          "pref": 0,
          "nopref": 0
        },
        "gt7": {
          "pref": 0,
          "nopref": 0
        }
      }
    },
    "buckets": [
      "lt2",
      "b23",
      "b35",
      "b57",
      "gt7"
    ],
    "bucket_labels": {
      "lt2": "< 2 prac. dnů",
      "b23": "2-3 prac. dnů",
      "b35": "3-5 prac. dnů",
      "b57": "5-7 prac. dnů",
      "gt7": "> 7 prac. dnů"
    }
  },
  "audit_order_expected": {
    "today_iso": "2026-05-28",
    "days_back": 5,
    "days_fwd": 7,
    "max_count": 19,
    "days": [
      {
        "date": "2026-05-23",
        "label": "23.5.",
        "dow": "so",
        "offset": -5,
        "status": "overdue",
        "pref": 0,
        "nopref": 0,
        "total": 0,
        "countries": {},
        "cases": []
      },
      {
        "date": "2026-05-24",
        "label": "24.5.",
        "dow": "ne",
        "offset": -4,
        "status": "overdue",
        "pref": 0,
        "nopref": 0,
        "total": 0,
        "countries": {},
        "cases": []
      },
      {
        "date": "2026-05-25",
        "label": "25.5.",
        "dow": "po",
        "offset": -3,
        "status": "overdue",
        "pref": 0,
        "nopref": 0,
        "total": 0,
        "countries": {},
        "cases": []
      },
      {
        "date": "2026-05-26",
        "label": "26.5.",
        "dow": "út",
        "offset": -2,
        "status": "overdue",
        "pref": 4,
        "nopref": 0,
        "total": 4,
        "countries": {
          "DE": 4
        },
        "cases": [
          {
            "id": "500MI00000ngYPGYA2",
            "cn": "00182403",
            "country": "DE",
            "pref": true
          },
          {
            "id": "500MI00000ndx45YAA",
            "cn": "00182291",
            "country": "DE",
            "pref": true
          },
          {
            "id": "500MI00000neSUPYA2",
            "cn": "00182319",
            "country": "DE",
            "pref": true
          },
          {
            "id": "500MI00000ncv97YAA",
            "cn": "00182180",
            "country": "DE",
            "pref": true
          }
        ]
      },
      {
        "date": "2026-05-27",
        "label": "27.5.",
        "dow": "st",
        "offset": -1,
        "status": "overdue",
        "pref": 4,
        "nopref": 1,
        "total": 5,
        "countries": {
          "DE": 3,
          "CZ": 1,
          "NL": 1
        },
        "cases": [
          {
            "id": "500MI00000nuSzzYAE",
            "cn": "00183707",
            "country": "DE",
            "pref": true
          },
          {
            "id": "500MI00000nsCKvYAM",
            "cn": "00183483",
            "country": "DE",
            "pref": true
          },
          {
            "id": "500MI00000nuDrJYAU",
            "cn": "00183671",
            "country": "CZ",
            "pref": true
          },
          {
            "id": "500MI00000ngtdWYAQ",
            "cn": "00182483",
            "country": "DE",
            "pref": true
          },
          {
            "id": "500MI00000nwhhwYAA",
            "cn": "00183884",
            "country": "NL",
            "pref": false
          }
        ]
      },
      {
        "date": "2026-05-28",
        "label": "28.5.",
        "dow": "čt",
        "offset": 0,
        "status": "today",
        "pref": 12,
        "nopref": 4,
        "total": 16,
        "countries": {
          "DE": 14,
          "SE": 1,
          "NL": 1
        },
        "cases": [
          {
            "id": "500MI00000nowYZYAY",
            "cn": "00183125",
            "country": "DE",
            "pref": true
          },
          {
            "id": "500MI00000nrSA4YAM",
            "cn": "00183445",
            "country": "SE",
            "pref": true
          },
          {
            "id": "500MI00000ngz1FYAQ",
            "cn": "00182460",
            "country": "DE",
            "pref": true
          },
          {
            "id": "500MI00000nio9nYAA",
            "cn": "00182595",
            "country": "DE",
            "pref": true
          },
          {
            "id": "500MI00000nk0TsYAI",
            "cn": "00182678",
            "country": "DE",
            "pref": false
          },
          {
            "id": "500MI00000nk3V8YAI",
            "cn": "00182675",
            "country": "DE",
            "pref": true
          },
          {
            "id": "500MI00000nlO4JYAU",
            "cn": "00182760",
            "country": "DE",
            "pref": false
          },
          {
            "id": "500MI00000nlXSfYAM",
            "cn": "00182800",
            "country": "DE",
            "pref": false
          },
          {
            "id": "500MI00000nmMJoYAM",
            "cn": "00182847",
            "country": "DE",
            "pref": true
          },
          {
            "id": "500MI00000noI7BYAU",
            "cn": "00183021",
            "country": "DE",
            "pref": true
          },
          {
            "id": "500MI00000npFKFYA2",
            "cn": "00183140",
            "country": "DE",
            "pref": true
          },
          {
            "id": "500MI00000npq6nYAA",
            "cn": "00183202",
            "country": "DE",
            "pref": true
          },
          {
            "id": "500MI00000npugkYAA",
            "cn": "00183246",
            "country": "DE",
            "pref": true
          },
          {
            "id": "500MI00000nqQk0YAE",
            "cn": "00183307",
            "country": "DE",
            "pref": true
          },
          {
            "id": "500MI00000nrIMAYA2",
            "cn": "00183475",
            "country": "DE",
            "pref": true
          },
          {
            "id": "500MI00000nu6t5YAA",
            "cn": "00183658",
            "country": "NL",
            "pref": false
          }
        ]
      },
      {
        "date": "2026-05-29",
        "label": "29.5.",
        "dow": "pá",
        "offset": 1,
        "status": "future",
        "pref": 12,
        "nopref": 7,
        "total": 19,
        "countries": {
          "DE": 13,
          "BE": 2,
          "AT": 2,
          "SK": 1,
          "IT": 1
        },
        "cases": [
          {
            "id": "500MI00000nrGPJYA2",
            "cn": "00183400",
            "country": "DE",
            "pref": false
          },
          {
            "id": "500MI00000nxiqSYAQ",
            "cn": "00183990",
            "country": "DE",
            "pref": false
          },
          {
            "id": "500MI00000npBDKYA2",
            "cn": "00183119",
            "country": "DE",
            "pref": true
          },
          {
            "id": "500MI00000nmSSSYA2",
            "cn": "00182865",
            "country": "DE",
            "pref": true
          },
          {
            "id": "500MI00000nsCb3YAE",
            "cn": "00183484",
            "country": "DE",
            "pref": true
          },
          {
            "id": "500MI00000ntb1IYAQ",
            "cn": "00183618",
            "country": "DE",
            "pref": false
          },
          {
            "id": "500MI00000ntkZ6YAI",
            "cn": "00183620",
            "country": "DE",
            "pref": true
          },
          {
            "id": "500MI00000nxmSfYAI",
            "cn": "00184012",
            "country": "BE",
            "pref": true
          },
          {
            "id": "500MI00000nkrF9YAI",
            "cn": "00182731",
            "country": "DE",
            "pref": true
          },
          {
            "id": "500MI00000nwWg8YAE",
            "cn": "00183885",
            "country": "DE",
            "pref": true
          },
          {
            "id": "500MI00000ncxvoYAA",
            "cn": "00182225",
            "country": "DE",
            "pref": false
          },
          {
            "id": "500MI00000nwzN5YAI",
            "cn": "00183898",
            "country": "DE",
            "pref": true
          },
          {
            "id": "500MI00000nub0pYAA",
            "cn": "00183734",
            "country": "AT",
            "pref": false
          },
          {
            "id": "500MI00000nvrMtYAI",
            "cn": "00183848",
            "country": "AT",
            "pref": true
          },
          {
            "id": "500MI00000nw2GaYAI",
            "cn": "00183858",
            "country": "DE",
            "pref": true
          },
          {
            "id": "500MI00000npEw9YAE",
            "cn": "00183168",
            "country": "SK",
            "pref": true
          },
          {
            "id": "500MI00000nw2JmYAI",
            "cn": "00183850",
            "country": "DE",
            "pref": true
          },
          {
            "id": "500MI00000nr9XNYAY",
            "cn": "00183408",
            "country": "BE",
            "pref": false
          },
          {
            "id": "500MI00000nhEYEYA2",
            "cn": "00182495",
            "country": "IT",
            "pref": false
          }
        ]
      },
      {
        "date": "2026-05-30",
        "label": "30.5.",
        "dow": "so",
        "offset": 2,
        "status": "future",
        "pref": 0,
        "nopref": 0,
        "total": 0,
        "countries": {},
        "cases": []
      },
      {
        "date": "2026-05-31",
        "label": "31.5.",
        "dow": "ne",
        "offset": 3,
        "status": "future",
        "pref": 0,
        "nopref": 0,
        "total": 0,
        "countries": {},
        "cases": []
      },
      {
        "date": "2026-06-01",
        "label": "1.6.",
        "dow": "po",
        "offset": 4,
        "status": "future",
        "pref": 0,
        "nopref": 1,
        "total": 1,
        "countries": {
          "PL": 1
        },
        "cases": [
          {
            "id": "500MI00000nugq2YAA",
            "cn": "00183718",
            "country": "PL",
            "pref": false
          }
        ]
      },
      {
        "date": "2026-06-02",
        "label": "2.6.",
        "dow": "út",
        "offset": 5,
        "status": "future",
        "pref": 0,
        "nopref": 0,
        "total": 0,
        "countries": {},
        "cases": []
      },
      {
        "date": "2026-06-03",
        "label": "3.6.",
        "dow": "st",
        "offset": 6,
        "status": "future",
        "pref": 0,
        "nopref": 0,
        "total": 0,
        "countries": {},
        "cases": []
      },
      {
        "date": "2026-06-04",
        "label": "4.6.",
        "dow": "čt",
        "offset": 7,
        "status": "future",
        "pref": 0,
        "nopref": 0,
        "total": 0,
        "countries": {},
        "cases": []
      }
    ],
    "overflow_back": {
      "pref": 0,
      "nopref": 0
    },
    "overflow_fwd": {
      "pref": 0,
      "nopref": 0
    },
    "totals": {
      "overdue": 9,
      "overdue_pref": 8,
      "overdue_days_count": 2,
      "max_overdue_days_back": 2,
      "today": 16,
      "today_pref": 12,
      "tomorrow": 19,
      "tomorrow_pref": 12,
      "week": 36,
      "total": 45
    }
  },
  "cebia_audit_order_expected": {
    "today_iso": "2026-05-28",
    "days_back": 5,
    "days_fwd": 7,
    "max_count": 4,
    "days": [
      {
        "date": "2026-05-23",
        "label": "23.5.",
        "dow": "so",
        "offset": -5,
        "status": "overdue",
        "pref": 0,
        "nopref": 0,
        "total": 0,
        "countries": {},
        "cases": []
      },
      {
        "date": "2026-05-24",
        "label": "24.5.",
        "dow": "ne",
        "offset": -4,
        "status": "overdue",
        "pref": 0,
        "nopref": 0,
        "total": 0,
        "countries": {},
        "cases": []
      },
      {
        "date": "2026-05-25",
        "label": "25.5.",
        "dow": "po",
        "offset": -3,
        "status": "overdue",
        "pref": 0,
        "nopref": 0,
        "total": 0,
        "countries": {},
        "cases": []
      },
      {
        "date": "2026-05-26",
        "label": "26.5.",
        "dow": "út",
        "offset": -2,
        "status": "overdue",
        "pref": 0,
        "nopref": 0,
        "total": 0,
        "countries": {},
        "cases": []
      },
      {
        "date": "2026-05-27",
        "label": "27.5.",
        "dow": "st",
        "offset": -1,
        "status": "overdue",
        "pref": 0,
        "nopref": 0,
        "total": 0,
        "countries": {},
        "cases": []
      },
      {
        "date": "2026-05-28",
        "label": "28.5.",
        "dow": "čt",
        "offset": 0,
        "status": "today",
        "pref": 0,
        "nopref": 4,
        "total": 4,
        "countries": {
          "CZ": 4
        },
        "cases": [
          {
            "id": "500MI00000nljSCYAY",
            "cn": "00182813",
            "country": "CZ",
            "pref": false
          },
          {
            "id": "500MI00000nqM0HYAU",
            "cn": "00183261",
            "country": "CZ",
            "pref": false
          },
          {
            "id": "500MI00000nrJZqYAM",
            "cn": "00183448",
            "country": "CZ",
            "pref": false
          },
          {
            "id": "500MI00000nsONlYAM",
            "cn": "00183524",
            "country": "CZ",
            "pref": false
          }
        ]
      },
      {
        "date": "2026-05-29",
        "label": "29.5.",
        "dow": "pá",
        "offset": 1,
        "status": "future",
        "pref": 0,
        "nopref": 0,
        "total": 0,
        "countries": {},
        "cases": []
      },
      {
        "date": "2026-05-30",
        "label": "30.5.",
        "dow": "so",
        "offset": 2,
        "status": "future",
        "pref": 0,
        "nopref": 0,
        "total": 0,
        "countries": {},
        "cases": []
      },
      {
        "date": "2026-05-31",
        "label": "31.5.",
        "dow": "ne",
        "offset": 3,
        "status": "future",
        "pref": 0,
        "nopref": 0,
        "total": 0,
        "countries": {},
        "cases": []
      },
      {
        "date": "2026-06-01",
        "label": "1.6.",
        "dow": "po",
        "offset": 4,
        "status": "future",
        "pref": 0,
        "nopref": 2,
        "total": 2,
        "countries": {
          "CZ": 2
        },
        "cases": [
          {
            "id": "500MI00000nxHf3YAE",
            "cn": "00183934",
            "country": "CZ",
            "pref": false
          },
          {
            "id": "500MI00000nxVLRYA2",
            "cn": "00183982",
            "country": "CZ",
            "pref": false
          }
        ]
      },
      {
        "date": "2026-06-02",
        "label": "2.6.",
        "dow": "út",
        "offset": 5,
        "status": "future",
        "pref": 0,
        "nopref": 0,
        "total": 0,
        "countries": {},
        "cases": []
      },
      {
        "date": "2026-06-03",
        "label": "3.6.",
        "dow": "st",
        "offset": 6,
        "status": "future",
        "pref": 0,
        "nopref": 0,
        "total": 0,
        "countries": {},
        "cases": []
      },
      {
        "date": "2026-06-04",
        "label": "4.6.",
        "dow": "čt",
        "offset": 7,
        "status": "future",
        "pref": 0,
        "nopref": 0,
        "total": 0,
        "countries": {},
        "cases": []
      }
    ],
    "overflow_back": {
      "pref": 0,
      "nopref": 0
    },
    "overflow_fwd": {
      "pref": 0,
      "nopref": 0
    },
    "totals": {
      "overdue": 0,
      "overdue_pref": 0,
      "overdue_days_count": 0,
      "max_overdue_days_back": 0,
      "today": 4,
      "today_pref": 0,
      "tomorrow": 0,
      "tomorrow_pref": 0,
      "week": 6,
      "total": 6
    }
  },
  "prep_to_done_daily": {
    "today_iso": "2026-05-27",
    "days": [
      {
        "date": "2026-05-27",
        "label": "27.5.",
        "dow": "st"
      },
      {
        "date": "2026-05-26",
        "label": "26.5.",
        "dow": "út"
      },
      {
        "date": "2026-05-25",
        "label": "25.5.",
        "dow": "po"
      },
      {
        "date": "2026-05-22",
        "label": "22.5.",
        "dow": "pá"
      },
      {
        "date": "2026-05-21",
        "label": "21.5.",
        "dow": "čt"
      },
      {
        "date": "2026-05-20",
        "label": "20.5.",
        "dow": "st"
      },
      {
        "date": "2026-05-19",
        "label": "19.5.",
        "dow": "út"
      },
      {
        "date": "2026-05-18",
        "label": "18.5.",
        "dow": "po"
      },
      {
        "date": "2026-05-15",
        "label": "15.5.",
        "dow": "pá"
      },
      {
        "date": "2026-05-14",
        "label": "14.5.",
        "dow": "čt"
      },
      {
        "date": "2026-05-13",
        "label": "13.5.",
        "dow": "st"
      },
      {
        "date": "2026-05-12",
        "label": "12.5.",
        "dow": "út"
      },
      {
        "date": "2026-05-11",
        "label": "11.5.",
        "dow": "po"
      },
      {
        "date": "2026-05-08",
        "label": "8.5.",
        "dow": "pá"
      }
    ],
    "carvago": {
      "users": [
        {
          "name": "Daniel Forman",
          "by_date": {
            "2026-05-27": 9,
            "2026-05-26": 8,
            "2026-05-25": 10,
            "2026-05-22": 8,
            "2026-05-21": 0,
            "2026-05-20": 0,
            "2026-05-19": 7,
            "2026-05-18": 8,
            "2026-05-15": 7,
            "2026-05-14": 1,
            "2026-05-13": 0,
            "2026-05-12": 6,
            "2026-05-11": 6,
            "2026-05-08": 5
          },
          "total": 75
        },
        {
          "name": "Marek Moťovský",
          "by_date": {
            "2026-05-27": 9,
            "2026-05-26": 7,
            "2026-05-25": 8,
            "2026-05-22": 7,
            "2026-05-21": 0,
            "2026-05-20": 0,
            "2026-05-19": 6,
            "2026-05-18": 9,
            "2026-05-15": 7,
            "2026-05-14": 1,
            "2026-05-13": 0,
            "2026-05-12": 5,
            "2026-05-11": 10,
            "2026-05-08": 6
          },
          "total": 75
        },
        {
          "name": "Daniel Noga",
          "by_date": {
            "2026-05-27": 3,
            "2026-05-26": 1,
            "2026-05-25": 1,
            "2026-05-22": 0,
            "2026-05-21": 0,
            "2026-05-20": 0,
            "2026-05-19": 6,
            "2026-05-18": 7,
            "2026-05-15": 3,
            "2026-05-14": 0,
            "2026-05-13": 0,
            "2026-05-12": 5,
            "2026-05-11": 7,
            "2026-05-08": 7
          },
          "total": 40
        },
        {
          "name": "Martin Farkas",
          "by_date": {
            "2026-05-27": 6,
            "2026-05-26": 0,
            "2026-05-25": 0,
            "2026-05-22": 8,
            "2026-05-21": 0,
            "2026-05-20": 0,
            "2026-05-19": 10,
            "2026-05-18": 6,
            "2026-05-15": 0,
            "2026-05-14": 0,
            "2026-05-13": 0,
            "2026-05-12": 0,
            "2026-05-11": 0,
            "2026-05-08": 0
          },
          "total": 30
        },
        {
          "name": "Drin Mucolli",
          "by_date": {
            "2026-05-27": 0,
            "2026-05-26": 2,
            "2026-05-25": 0,
            "2026-05-22": 0,
            "2026-05-21": 0,
            "2026-05-20": 0,
            "2026-05-19": 2,
            "2026-05-18": 1,
            "2026-05-15": 0,
            "2026-05-14": 0,
            "2026-05-13": 0,
            "2026-05-12": 1,
            "2026-05-11": 1,
            "2026-05-08": 1
          },
          "total": 8
        },
        {
          "name": "Arbios Islami",
          "by_date": {
            "2026-05-27": 0,
            "2026-05-26": 1,
            "2026-05-25": 2,
            "2026-05-22": 2,
            "2026-05-21": 0,
            "2026-05-20": 0,
            "2026-05-19": 0,
            "2026-05-18": 1,
            "2026-05-15": 0,
            "2026-05-14": 0,
            "2026-05-13": 0,
            "2026-05-12": 0,
            "2026-05-11": 0,
            "2026-05-08": 0
          },
          "total": 6
        },
        {
          "name": "Erion Rexhepi",
          "by_date": {
            "2026-05-27": 1,
            "2026-05-26": 0,
            "2026-05-25": 1,
            "2026-05-22": 1,
            "2026-05-21": 0,
            "2026-05-20": 0,
            "2026-05-19": 0,
            "2026-05-18": 0,
            "2026-05-15": 1,
            "2026-05-14": 0,
            "2026-05-13": 0,
            "2026-05-12": 1,
            "2026-05-11": 0,
            "2026-05-08": 0
          },
          "total": 5
        },
        {
          "name": "Vladimír Uher",
          "by_date": {
            "2026-05-27": 0,
            "2026-05-26": 0,
            "2026-05-25": 2,
            "2026-05-22": 3,
            "2026-05-21": 0,
            "2026-05-20": 0,
            "2026-05-19": 0,
            "2026-05-18": 0,
            "2026-05-15": 0,
            "2026-05-14": 0,
            "2026-05-13": 0,
            "2026-05-12": 0,
            "2026-05-11": 0,
            "2026-05-08": 0
          },
          "total": 5
        }
      ],
      "day_totals": [
        28,
        19,
        24,
        29,
        0,
        0,
        31,
        32,
        18,
        2,
        0,
        18,
        24,
        19
      ],
      "max_cell": 10
    },
    "cebia": {
      "users": [
        {
          "name": "Daniel Noga",
          "by_date": {
            "2026-05-27": 1,
            "2026-05-26": 3,
            "2026-05-25": 4,
            "2026-05-22": 0,
            "2026-05-21": 0,
            "2026-05-20": 0,
            "2026-05-19": 2,
            "2026-05-18": 2,
            "2026-05-15": 1,
            "2026-05-14": 0,
            "2026-05-13": 0,
            "2026-05-12": 1,
            "2026-05-11": 1,
            "2026-05-08": 1
          },
          "total": 16
        },
        {
          "name": "Martin Farkas",
          "by_date": {
            "2026-05-27": 2,
            "2026-05-26": 0,
            "2026-05-25": 0,
            "2026-05-22": 1,
            "2026-05-21": 0,
            "2026-05-20": 0,
            "2026-05-19": 2,
            "2026-05-18": 0,
            "2026-05-15": 1,
            "2026-05-14": 0,
            "2026-05-13": 0,
            "2026-05-12": 0,
            "2026-05-11": 0,
            "2026-05-08": 0
          },
          "total": 6
        },
        {
          "name": "Marek Moťovský",
          "by_date": {
            "2026-05-27": 0,
            "2026-05-26": 1,
            "2026-05-25": 2,
            "2026-05-22": 1,
            "2026-05-21": 0,
            "2026-05-20": 0,
            "2026-05-19": 0,
            "2026-05-18": 0,
            "2026-05-15": 1,
            "2026-05-14": 0,
            "2026-05-13": 0,
            "2026-05-12": 0,
            "2026-05-11": 0,
            "2026-05-08": 1
          },
          "total": 6
        }
      ],
      "day_totals": [
        3,
        4,
        6,
        2,
        0,
        0,
        4,
        2,
        3,
        0,
        0,
        1,
        1,
        2
      ],
      "max_cell": 4
    }
  }
}